{
  "type": "minecraft:crafting_shapeless",
  
  "ingredients": [
  
    {"item": "minecraft:diamond"},
    {"item": "minecraft:diamond"},
    {"item": "minecraft:emerald"},
    {"item": "minecraft:emerald"},
    {"item": "nightsouls:pure_saitastone_ingot"},
    {"item": "nightsouls:pure_miizealite_ingot"},
    {"item": "nightsouls:pure_cranite_ingot"},
    {"item": "nightsouls:pure_bastirite_ingot"},
    {"item": "minecraft:wheat_seeds"}
    
  ],
  
  "result": {
    "item": "nightsouls:crystal_seeds",
    "count": 2
  }
}